oni/__init__.py
oni/brand.py
oni/cli.py
oni/coherence.py
oni/firewall.py
oni/layers.py
oni/neuromapping.py
oni/scale_freq.py
oni/neurosecurity/__init__.py
oni/neurosecurity/anonymizer.py
oni/neurosecurity/consent.py
oni/neurosecurity/firewall.py
oni/neurosecurity/privacy_score.py
oni/neurosecurity/threats.py
oni/ui/__init__.py
oni/ui/app.py
oni/ui/styles.py
oni_framework-0.2.6.dist-info/METADATA
oni_framework-0.2.6.dist-info/WHEEL
oni_framework-0.2.6.dist-info/entry_points.txt
oni_framework-0.2.6.dist-info/top_level.txt
oni_framework-0.2.6.dist-info/RECORD
