Metadata-Version: 2.4
Name: oni-framework
Version: 0.2.6
Summary: Cₛ Core - Mathematical API for detection signatures and anomaly validation in brain-computer interfaces. Build security rules using coherence scoring (Cₛ) and scale-frequency invariant (f×S≈k) equations.
Author: Kevin L. Qi
Maintainer: Kevin L. Qi
License: Apache-2.0
Project-URL: Homepage, https://qikevinl.github.io/ONI/
Project-URL: Documentation, https://github.com/qikevinl/ONI/tree/main/MAIN/oni-framework
Project-URL: Repository, https://github.com/qikevinl/ONI
Project-URL: Issues, https://github.com/qikevinl/ONI/issues
Project-URL: Changelog, https://github.com/qikevinl/ONI/blob/main/MAIN/oni-framework/CHANGELOG.md
Keywords: brain-computer-interface,BCI,neural-security,neurosecurity,neuroethics,neuroscience,cybersecurity,signal-processing,coherence-metric,neural-firewall,privacy,EEG,neural-interface,medical-device-security
Classifier: Development Status :: 4 - Beta
Classifier: Intended Audience :: Science/Research
Classifier: Intended Audience :: Developers
Classifier: Intended Audience :: Healthcare Industry
Classifier: License :: OSI Approved :: Apache Software License
Classifier: Operating System :: OS Independent
Classifier: Programming Language :: Python :: 3
Classifier: Programming Language :: Python :: 3.9
Classifier: Programming Language :: Python :: 3.10
Classifier: Programming Language :: Python :: 3.11
Classifier: Programming Language :: Python :: 3.12
Classifier: Topic :: Scientific/Engineering :: Bio-Informatics
Classifier: Topic :: Scientific/Engineering :: Medical Science Apps.
Classifier: Topic :: Security
Classifier: Topic :: Scientific/Engineering :: Artificial Intelligence
Classifier: Typing :: Typed
Requires-Python: >=3.9
Provides-Extra: dev
Requires-Dist: pytest>=7.0; extra == "dev"
Requires-Dist: pytest-cov>=4.0; extra == "dev"
Requires-Dist: black>=23.0; extra == "dev"
Requires-Dist: isort>=5.0; extra == "dev"
Requires-Dist: mypy>=1.0; extra == "dev"
Provides-Extra: viz
Requires-Dist: matplotlib>=3.5; extra == "viz"
Requires-Dist: numpy>=1.21; extra == "viz"
Provides-Extra: all
Requires-Dist: oni-framework[dev,viz]; extra == "all"
